lvmopstools/__init__.py
lvmopstools/__main__.py
lvmopstools/actor.py
lvmopstools/clu.py
lvmopstools/ds9.py
lvmopstools/ephemeris.py
lvmopstools/influxdb.py
lvmopstools/kubernetes.py
lvmopstools/notifications.py
lvmopstools/pubsub.py
lvmopstools/retrier.py
lvmopstools/slack.py
lvmopstools/socket.py
lvmopstools/utils.py
lvmopstools/weather.py
lvmopstools/data/config.yaml
lvmopstools/data/critical_error_email_template.html
lvmopstools/data/ephemeris_59945_62866.parquet
lvmopstools/devices/__init__.py
lvmopstools/devices/ags.py
lvmopstools/devices/ion.py
lvmopstools/devices/nps.py
lvmopstools/devices/specs.py
lvmopstools/devices/switch.py
lvmopstools/devices/thermistors.py
lvmopstools-0.5.21.dist-info/METADATA
lvmopstools-0.5.21.dist-info/WHEEL
lvmopstools-0.5.21.dist-info/entry_points.txt
lvmopstools-0.5.21.dist-info/licenses/LICENSE.md
lvmopstools-0.5.21.dist-info/RECORD
